osam/__init__.py
osam/__main__.py
osam/__main___test.py
osam/_contextlib.py
osam/_humanize.py
osam/_json.py
osam/_json_test.py
osam/_server.py
osam/_tabulate.py
osam/apis.py
osam/apis_test.py
osam/_data/dogs.jpg
osam/_models/__init__.py
osam/_models/efficientsam/LICENSE
osam/_models/efficientsam/__init__.py
osam/_models/efficientsam/_decoding.py
osam/_models/efficientsam/_encoding.py
osam/_models/efficientsam/_models.py
osam/_models/sam/LICENSE
osam/_models/sam/__init__.py
osam/_models/sam/_decoding.py
osam/_models/sam/_encoding.py
osam/_models/sam/_images.py
osam/_models/sam/_models.py
osam/_models/sam2/LICENSE
osam/_models/sam2/__init__.py
osam/_models/sam2/_decoding.py
osam/_models/sam2/_encoding.py
osam/_models/sam2/_models.py
osam/_models/yoloworld/LICENSE
osam/_models/yoloworld/__init__.py
osam/_models/yoloworld/clip/LICENSE
osam/_models/yoloworld/clip/__init__.py
osam/_models/yoloworld/clip/bpe_simple_vocab_16e6.txt.gz
osam/_models/yoloworld/clip/clip.py
osam/_models/yoloworld/clip/simple_tokenizer.py
osam/types/__init__.py
osam/types/_annotation.py
osam/types/_blob.py
osam/types/_bounding_box.py
osam/types/_generate.py
osam/types/_image_embedding.py
osam/types/_model.py
osam/types/_prompt.py
osam-0.2.3.dist-info/METADATA
osam-0.2.3.dist-info/WHEEL
osam-0.2.3.dist-info/entry_points.txt
osam-0.2.3.dist-info/licenses/LICENSE
osam-0.2.3.dist-info/RECORD
