Metadata-Version: 2.4
Name: osam
Version: 0.2.3
Summary: Get up and running vision foundational models locally.
Project-URL: Homepage, https://github.com/wkentaro/osam
Author-email: Kentaro Wada <www.kentaro.wada@gmail.com>
License: MIT
License-File: LICENSE
Classifier: Development Status :: 3 - Alpha
Classifier: Environment :: Console
Classifier: Intended Audience :: Developers
Classifier: License :: OSI Approved :: MIT License
Classifier: Operating System :: OS Independent
Classifier: Programming Language :: Python
Classifier: Programming Language :: Python :: 3 :: Only
Classifier: Programming Language :: Python :: 3.8
Classifier: Programming Language :: Python :: 3.9
Classifier: Programming Language :: Python :: 3.10
Classifier: Programming Language :: Python :: 3.11
Classifier: Programming Language :: Python :: 3.12
Classifier: Topic :: Software Development :: Libraries :: Python Modules
Requires-Python: >=3.9
Requires-Dist: click
Requires-Dist: gdown
Requires-Dist: imgviz
Requires-Dist: loguru
Requires-Dist: onnxruntime!=1.16.0,!=1.20.0,!=1.20.1,>=1.14.1
Requires-Dist: pillow
Requires-Dist: pydantic
Provides-Extra: serve
Requires-Dist: fastapi; extra == 'serve'
Requires-Dist: uvicorn; extra == 'serve'
